{
    "9": [
        0,
        3,
        7,
        14,
        15,
        16,
        18,
        26,
        28,
        29,
        44,
        58,
        59,
        60,
        66,
        67,
        68,
        82,
        86,
        91,
        92,
        94,
        95
    ],
    "7": [
        1,
        21,
        30,
        32,
        47,
        56,
        70,
        78,
        98
    ],
    "1": [
        2,
        9,
        31,
        40,
        48,
        62,
        69,
        72,
        75,
        81,
        83,
        89,
        96
    ],
    "0": [
        4,
        11,
        38,
        57,
        74,
        88,
        93
    ],
    "2": [
        5,
        6,
        20,
        24,
        33,
        34,
        36,
        37,
        43,
        51,
        64,
        65,
        77
    ],
    "4": [
        8,
        22,
        25,
        45,
        46,
        54,
        61,
        71,
        79,
        80,
        87
    ],
    "3": [
        10,
        17,
        19,
        23,
        35,
        42,
        90
    ],
    "8": [
        12,
        27,
        50,
        52,
        55,
        76,
        99
    ],
    "6": [
        13,
        39,
        41,
        49,
        63,
        73,
        84
    ],
    "5": [
        53,
        85,
        97
    ]
}