{
    "5": [
        0,
        2,
        11,
        14,
        17,
        18,
        22,
        44,
        47,
        50,
        52,
        77,
        79,
        86,
        92
    ],
    "7": [
        1,
        24,
        27,
        43,
        67,
        72,
        80,
        88,
        90
    ],
    "8": [
        3,
        8,
        20,
        35,
        39,
        46,
        63
    ],
    "4": [
        4,
        5,
        6,
        13,
        15,
        26,
        37,
        41,
        42,
        45,
        66,
        69,
        73,
        81,
        83,
        89,
        93
    ],
    "9": [
        7,
        19,
        36,
        59,
        62,
        68,
        71,
        76,
        85,
        94
    ],
    "6": [
        9,
        10,
        30,
        32,
        34,
        55,
        74,
        75,
        78,
        82,
        98,
        99
    ],
    "2": [
        12,
        29,
        31,
        38,
        49,
        51,
        54,
        64,
        65,
        70,
        87,
        96
    ],
    "1": [
        16,
        21,
        25,
        33,
        48,
        97
    ],
    "3": [
        23,
        28,
        53,
        57,
        58,
        60,
        84,
        91,
        95
    ],
    "0": [
        40,
        56,
        61
    ]
}